[
  {
    "@id": "https://w3id.org/hpdb/api/items/871e2d4eb23aba43b66a2ba3f1c49d3c",
    "@type": [
      "https://w3id.org/hpdb/api/classes/Item"
    ],
    "http://purl.org/dc/terms/identifer": [
      {
        "@value": "871e2d4eb23aba43b66a2ba3f1c49d3c"
      }
    ],
    "http://schema.org/image": [
      {
        "@id": "https://iiif.dl.itc.u-tokyo.ac.jp/iiif/asia/hp/2/2_067.tif/938,2096,3892,489/,200/0/default.jpg"
      }
    ],
    "http://schema.org/relationLink": [
      {
        "@id": "http://w3id.org/hpdb/item/871e2d4eb23aba43b66a2ba3f1c49d3c"
      }
    ],
    "http://schema.org/url": [
      {
        "@id": "http://codh.rois.ac.jp/software/iiif-curation-viewer/demo/?curation=https://moeller.jinsha.tsukuba.ac.jp/data/curation.json&pos=978"
      }
    ],
    "http://www.w3.org/2000/01/rdf-schema#label": [
      {
        "@value": "871e2d4eb23aba43b66a2ba3f1c49d3c"
      }
    ],
    "https://w3id.org/hpdb/api/properties/hieroglyphNo": [
      {
        "@id": "https://w3id.org/hpdb/api/term/hieroglyphNo/D60"
      }
    ],
    "https://w3id.org/hpdb/api/properties/möllerNo": [
      {
        "@id": "https://w3id.org/hpdb/api/term/möllerNo/500"
      }
    ],
    "https://w3id.org/hpdb/api/properties/notes": [
      {
        "@value": "499(D60)+124(D58).  See 499(W54)"
      }
    ],
    "https://w3id.org/hpdb/api/properties/phonetic": [
      {
        "@value": "wab"
      }
    ],
    "https://w3id.org/hpdb/api/properties/vol": [
      {
        "@value": 2
      }
    ]
  }
]