[
  {
    "@id": "https://w3id.org/hpdb/api/items/c5d51e7cb1310ee689be996268b654dd",
    "@type": [
      "https://w3id.org/hpdb/api/classes/Item"
    ],
    "http://purl.org/dc/terms/identifer": [
      {
        "@value": "c5d51e7cb1310ee689be996268b654dd"
      }
    ],
    "http://schema.org/image": [
      {
        "@id": "https://iiif.dl.itc.u-tokyo.ac.jp/iiif/asia/hp/1/1_043.tif/904,3532,3888,500/,200/0/default.jpg"
      }
    ],
    "http://schema.org/relation": [
      {
        "@id": "http://codh.rois.ac.jp/software/iiif-curation-viewer/demo/?curation=https://moeller.jinsha.tsukuba.ac.jp/data/curation.json&pos=122"
      }
    ],
    "http://www.w3.org/2000/01/rdf-schema#label": [
      {
        "@value": "c5d51e7cb1310ee689be996268b654dd"
      }
    ],
    "https://w3id.org/hpdb/api/properties/hieroglyphNo": [
      {
        "@id": "https://w3id.org/hpdb/api/term/hieroglyphNo/E21"
      }
    ],
    "https://w3id.org/hpdb/api/properties/möllerNo": [
      {
        "@id": "https://w3id.org/hpdb/api/term/möllerNo/144"
      }
    ],
    "https://w3id.org/hpdb/api/properties/phonetic": [
      {
        "@value": "stX"
      },
      {
        "@value": "stS"
      }
    ],
    "https://w3id.org/hpdb/api/properties/vol": [
      {
        "@value": 1
      }
    ]
  }
]