[
  {
    "@id": "https://w3id.org/hpdb/api/term/itemNo/504",
    "@type": [
      "https://w3id.org/hpdb/api/classes/ItemNo"
    ],
    "http://www.w3.org/2000/01/rdf-schema#label": [
      {
        "@value": "504"
      }
    ]
  },
  {
    "@id": "https://w3id.org/hpdb/api/term/hieroglyphNo/W17",
    "@type": [
      "https://w3id.org/hpdb/api/classes/HieroglyphNo"
    ],
    "http://www.w3.org/2000/01/rdf-schema#label": [
      {
        "@value": "W17"
      }
    ],
    "https://w3id.org/hpdb/api/properties/categoryClass": [
      {
        "@id": "https://w3id.org/hpdb/api/term/categoryClass/W"
      }
    ]
  },
  {
    "@id": "https://w3id.org/hpdb/api/term/categoryClass/W",
    "@type": [
      "https://w3id.org/hpdb/api/classes/Category"
    ],
    "http://www.w3.org/2000/01/rdf-schema#label": [
      {
        "@value": "W"
      }
    ]
  },
  {
    "@id": "https://w3id.org/hpdb/api/term/hieraticNo/504",
    "@type": [
      "https://w3id.org/hpdb/api/classes/HieraticNo"
    ],
    "http://www.w3.org/2000/01/rdf-schema#label": [
      {
        "@value": "504"
      }
    ],
    "https://w3id.org/hpdb/api/properties/phonetic": [
      {
        "@value": "xnt"
      }
    ]
  },
  {
    "@id": "https://w3id.org/hpdb/api/items/348006",
    "@type": [
      "https://w3id.org/hpdb/api/classes/Item"
    ],
    "http://schema.org/image": [
      {
        "@id": "https://iiif.dl.itc.u-tokyo.ac.jp/iiif/asia/hp/3/3_070.tif/939,3477,3923,480/,200/0/default.jpg"
      }
    ],
    "http://schema.org/license": [
      {
        "@id": "http://creativecommons.org/licenses/by/4.0/"
      }
    ],
    "http://schema.org/relatedLink": [
      {
        "@id": "http://codh.rois.ac.jp/software/iiif-curation-viewer/demo/?manifest=https://moeller.jinsha.tsukuba.ac.jp/data/manifest/8aaa203c-1c5a-4fef-973b-4fb174d60d37/manifest.json&canvas=https://iiif.dl.itc.u-tokyo.ac.jp/repo/iiif/8aaa203c-1c5a-4fef-973b-4fb174d60d37/canvas/p70&xywh=939,3477,3923,480&xywh_highlight=border"
      }
    ],
    "http://schema.org/url": [
      {
        "@id": "http://w3id.org/hpdb/item/348006"
      }
    ],
    "http://www.w3.org/2000/01/rdf-schema#label": [
      {
        "@value": "348006"
      }
    ],
    "https://w3id.org/hpdb/api/properties/hieraticNo": [
      {
        "@id": "https://w3id.org/hpdb/api/term/hieraticNo/504"
      }
    ],
    "https://w3id.org/hpdb/api/properties/hieroglyphNo": [
      {
        "@id": "https://w3id.org/hpdb/api/term/hieroglyphNo/W17"
      },
      {
        "@id": "https://w3id.org/hpdb/api/term/hieroglyphNo/W18"
      }
    ],
    "https://w3id.org/hpdb/api/properties/itemNo": [
      {
        "@id": "https://w3id.org/hpdb/api/term/itemNo/504"
      }
    ],
    "https://w3id.org/hpdb/api/properties/itemType": [
      {
        "@value": "Main"
      }
    ],
    "https://w3id.org/hpdb/api/properties/order": [
      {
        "@value": 6
      }
    ],
    "https://w3id.org/hpdb/api/properties/page": [
      {
        "@value": 48
      }
    ],
    "https://w3id.org/hpdb/api/properties/unit": [
      {
        "@value": "Single"
      }
    ],
    "https://w3id.org/hpdb/api/properties/vol": [
      {
        "@value": 3
      }
    ]
  },
  {
    "@id": "https://w3id.org/hpdb/api/term/hieroglyphNo/W18",
    "@type": [
      "https://w3id.org/hpdb/api/classes/HieroglyphNo"
    ],
    "http://www.w3.org/2000/01/rdf-schema#label": [
      {
        "@value": "W18"
      }
    ],
    "https://w3id.org/hpdb/api/properties/categoryClass": [
      {
        "@id": "https://w3id.org/hpdb/api/term/categoryClass/W"
      }
    ]
  }
]