[
  {
    "@id": "https://w3id.org/hpdb/api/term/hieroglyphNo/G50",
    "@type": [
      "https://w3id.org/hpdb/api/classes/HieroglyphNo"
    ],
    "http://schema.org/description": [
      {
        "@value": "two plovers"
      }
    ],
    "http://schema.org/name": [
      {
        "@value": "𓅺"
      }
    ],
    "http://www.w3.org/2000/01/rdf-schema#label": [
      {
        "@value": "G50"
      }
    ],
    "https://w3id.org/hpdb/api/properties/phonetic": [
      {
        "@value": "Id. rḫtj"
      }
    ],
    "https://w3id.org/hpdb/api/properties/unicode": [
      {
        "@value": "U+1317A"
      }
    ]
  }
]