[
  {
    "@id": "https://nakamura196.github.io/hpdb4/data/38c76c0ca6d05702b031def19eba1a2d.json",
    "http://example.org/hieroglyphNo": [
      {
        "@id": "https://nakamura196.github.io/hpdb4/term/keyword/S29.json"
      }
    ],
    "http://example.org/identifier": [
      {
        "@value": "38c76c0ca6d05702b031def19eba1a2d"
      }
    ],
    "http://example.org/möllerNo": [
      {
        "@id": "https://nakamura196.github.io/hpdb4/term/möllerNo/432.json"
      }
    ],
    "http://example.org/phoneWord": [
      {
        "@value": "s"
      }
    ],
    "http://example.org/vol": [
      {
        "@value": 2
      }
    ],
    "http://schema.org/image": [
      {
        "@id": "https://iiif.dl.itc.u-tokyo.ac.jp/iiif/asia/hp/2/2_060.tif/972,3505,3909,485/,200/0/default.jpg"
      }
    ],
    "http://schema.org/relation": [
      {
        "@id": "http://codh.rois.ac.jp/software/iiif-curation-viewer/demo/?curation=https://moeller.jinsha.tsukuba.ac.jp/data/curation.json&pos=913"
      }
    ]
  }
]