[
  {
    "@id": "https://w3id.org/hpdb/api/items/6e9d029da32ec286c487cd62bc8121ef",
    "@type": [
      "https://w3id.org/hpdb/api/classes/Item"
    ],
    "http://purl.org/dc/terms/identifer": [
      {
        "@value": "6e9d029da32ec286c487cd62bc8121ef"
      }
    ],
    "http://schema.org/image": [
      {
        "@id": "https://iiif.dl.itc.u-tokyo.ac.jp/iiif/asia/hp/1/1_055.tif/924,1265,3884,485/,200/0/default.jpg"
      }
    ],
    "http://schema.org/relationLink": [
      {
        "@id": "http://w3id.org/hpdb/item/6e9d029da32ec286c487cd62bc8121ef"
      }
    ],
    "http://schema.org/url": [
      {
        "@id": "http://codh.rois.ac.jp/software/iiif-curation-viewer/demo/?curation=https://moeller.jinsha.tsukuba.ac.jp/data/curation.json&pos=231"
      }
    ],
    "http://www.w3.org/2000/01/rdf-schema#label": [
      {
        "@value": "6e9d029da32ec286c487cd62bc8121ef"
      }
    ],
    "https://w3id.org/hpdb/api/properties/hieroglyphNo": [
      {
        "@id": "https://w3id.org/hpdb/api/term/hieroglyphNo/L2"
      }
    ],
    "https://w3id.org/hpdb/api/properties/möllerNo": [
      {
        "@id": "https://w3id.org/hpdb/api/term/möllerNo/260"
      }
    ],
    "https://w3id.org/hpdb/api/properties/phonetic": [
      {
        "@value": "bit"
      }
    ],
    "https://w3id.org/hpdb/api/properties/vol": [
      {
        "@value": 1
      }
    ]
  }
]