[
  {
    "@id": "https://nakamura196.github.io/hpdb4/data/708db49b230f8510e618fc467aae65ce.json",
    "http://example.org/hieroglyphNo": [
      {
        "@id": "https://nakamura196.github.io/hpdb4/term/keyword/P4.json"
      }
    ],
    "http://example.org/identifier": [
      {
        "@value": "708db49b230f8510e618fc467aae65ce"
      }
    ],
    "http://example.org/möllerNo": [
      {
        "@id": "https://nakamura196.github.io/hpdb4/term/möllerNo/376.json"
      }
    ],
    "http://example.org/phoneWord": [
      {
        "@value": "wHa"
      }
    ],
    "http://example.org/vol": [
      {
        "@value": 2
      }
    ],
    "http://schema.org/image": [
      {
        "@id": "https://iiif.dl.itc.u-tokyo.ac.jp/iiif/asia/hp/2/2_055.tif/895,4870,3909,484/,200/0/default.jpg"
      }
    ],
    "http://schema.org/relation": [
      {
        "@id": "http://codh.rois.ac.jp/software/iiif-curation-viewer/demo/?curation=https://moeller.jinsha.tsukuba.ac.jp/data/curation.json&pos=867"
      }
    ]
  }
]